graia/broadcast/__init__.py
graia/broadcast/builtin/__init__.py
graia/broadcast/builtin/decorators.py
graia/broadcast/builtin/defer.py
graia/broadcast/builtin/depend.py
graia/broadcast/builtin/derive.py
graia/broadcast/builtin/event.py
graia/broadcast/creator.py
graia/broadcast/entities/__init__.py
graia/broadcast/entities/decorator.py
graia/broadcast/entities/dispatcher.py
graia/broadcast/entities/dispatcher.pyi
graia/broadcast/entities/event.py
graia/broadcast/entities/exectarget.py
graia/broadcast/entities/listener.py
graia/broadcast/entities/namespace.py
graia/broadcast/entities/signatures.py
graia/broadcast/exceptions.py
graia/broadcast/interfaces/__init__.py
graia/broadcast/interfaces/decorator.py
graia/broadcast/interfaces/dispatcher.py
graia/broadcast/interrupt/__init__.py
graia/broadcast/interrupt/waiter.py
graia/broadcast/priority.py
graia/broadcast/typing.py
graia/broadcast/utilles.py
graia_broadcast-0.23.5.dist-info/METADATA
graia_broadcast-0.23.5.dist-info/WHEEL
graia_broadcast-0.23.5.dist-info/entry_points.txt
graia_broadcast-0.23.5.dist-info/RECORD
